demo/__init__.py
explainers/__init__.py
models/NullRegressor.py
models/__init__.py
xaisuite/__init__.py
xaisuite/dataHandler.py
xaisuite/explainableModel.py
xaisuite/insightGenerator.py
xaisuite/xaisuiteFoundation.py
xaisuitegui/_init_.py
xaisuitegui/runner.py
XAISuite-2.9.2.dist-info/METADATA
XAISuite-2.9.2.dist-info/WHEEL
XAISuite-2.9.2.dist-info/top_level.txt
XAISuite-2.9.2.dist-info/RECORD
