Metadata-Version: 2.1
Name: XAISuite
Version: 2.9.2
Summary: XAISuite: Training and Explanation Generation Utilities for Machine Learning Models
Home-page: https://github.com/11301858/XAISuite
Author: Shreyan Mitra
Keywords: XAI Explainable AI Explanation Machine Learning Models
Requires-Dist: omnixai ==1.2.4
Requires-Dist: dash >=2.7.1
Requires-Dist: dash-bootstrap-components >=1.3.0
Requires-Dist: skorch >=0.12.1
Requires-Dist: torch >=2.0.0
Requires-Dist: scikeras >=0.10.0
Requires-Dist: seaborn ==0.12.2
